changelog_generator/__init__.py
changelog_generator/changelog_generator_enhanced.py
anantduggal_changelog_generator-1.0.0.dist-info/METADATA
anantduggal_changelog_generator-1.0.0.dist-info/WHEEL
anantduggal_changelog_generator-1.0.0.dist-info/entry_points.txt
anantduggal_changelog_generator-1.0.0.dist-info/licenses/LICENSE
anantduggal_changelog_generator-1.0.0.dist-info/RECORD
