Metadata-Version: 2.4
Name: anantduggal-changelog-generator
Version: 1.0.0
Summary: AI-powered changelog generator with smart caching and async processing
Project-URL: Homepage, https://github.com/anantduggal/changelog-generator
Project-URL: Documentation, https://github.com/anantduggal/changelog-generator#readme
Project-URL: Repository, https://github.com/anantduggal/changelog-generator
Project-URL: Issues, https://github.com/anantduggal/changelog-generator/issues
Project-URL: Changelog, https://github.com/anantduggal/changelog-generator/blob/main/CHANGELOG.md
Author-email: Anant Duggal <aduggal@uwaterloo.ca>
Maintainer-email: Anant Duggal <aduggal@uwaterloo.ca>
License: MIT
License-File: LICENSE
Keywords: ai,changelog,claude,cli,git,github
Classifier: Development Status :: 5 - Production/Stable
Classifier: Intended Audience :: Developers
Classifier: License :: OSI Approved :: MIT License
Classifier: Operating System :: OS Independent
Classifier: Programming Language :: Python :: 3
Classifier: Programming Language :: Python :: 3.9
Classifier: Programming Language :: Python :: 3.10
Classifier: Programming Language :: Python :: 3.11
Classifier: Programming Language :: Python :: 3.12
Classifier: Topic :: Software Development :: Documentation
Classifier: Topic :: Software Development :: Libraries :: Python Modules
Classifier: Topic :: System :: Systems Administration
Classifier: Topic :: Text Processing :: Markup
Classifier: Topic :: Utilities
Requires-Python: >=3.9
Requires-Dist: aiofiles<24.0.0,>=23.0.0
Requires-Dist: aiohttp<4.0.0,>=3.8.0
Requires-Dist: pyyaml<7.0.0,>=6.0.0
Requires-Dist: redis[hiredis]<5.0.0,>=4.5.0
Requires-Dist: requests<3.0.0,>=2.31.0
Requires-Dist: rich<14.0.0,>=13.0.0
Provides-Extra: dev
Requires-Dist: black>=23.0.0; extra == 'dev'
Requires-Dist: flake8>=6.0.0; extra == 'dev'
Requires-Dist: isort>=5.12.0; extra == 'dev'
Requires-Dist: mypy>=1.0.0; extra == 'dev'
Requires-Dist: pytest-asyncio>=0.21.0; extra == 'dev'
Requires-Dist: pytest>=7.0.0; extra == 'dev'
